Metadata-Version: 2.1
Name: HF_QuickUtils
Version: 0.1.3
Summary: A utils pack for downloading model form Huggingface mirror site in china
Home-page: https://pypi.org/project/HF_QuickUtils/
Author: MCqie
Author-email: qq1051846107@outlook.com
Classifier: Programming Language :: Python :: 3
Classifier: License :: OSI Approved :: MIT License
Classifier: Operating System :: OS Independent
Requires-Python: >=3.9
Requires-Dist: setuptools~=72.1.0
Requires-Dist: transformers~=4.44.2
Requires-Dist: huggingface-hub~=0.24.7
Requires-Dist: bs4~=0.0.2
Requires-Dist: gradio~=4.44.0
Requires-Dist: requests~=2.32.3
Requires-Dist: beautifulsoup4~=4.12.3
Requires-Dist: prettytable~=3.11.0
